napari_crop/__init__.py
napari_crop/_dock_widgets.py
napari_crop/_function.py
napari_crop/_utils.py
napari_crop/_version.py
napari_crop/napari.yaml
napari_crop/_tests/__init__.py
napari_crop/_tests/test_function.py
napari_crop/_tests/test_widget.py
napari_crop/notebooks/cut_with_plane_example.ipynb
napari_crop-0.1.12.dist-info/licenses/LICENSE
napari_crop-0.1.12.dist-info/METADATA
napari_crop-0.1.12.dist-info/WHEEL
napari_crop-0.1.12.dist-info/entry_points.txt
napari_crop-0.1.12.dist-info/top_level.txt
napari_crop-0.1.12.dist-info/RECORD
