Metadata-Version: 2.4
Name: napari-crop
Version: 0.1.12
Summary: Crop regions in napari manually
Author: Tim Morello, Marcelo Leomil Zoccoler, Johannes Soltwedel
Author-email: Robert Haase <robert.haase@tu-dresden.de>
License: 
Project-URL: Homepage, https://github.com/biapol/napari-crop
Project-URL: Bug Tracker, https://github.com/biapol/napari-crop/issues
Project-URL: Documentation, https://github.com/biapol/napari-crop#README.md
Project-URL: Source Code, https://github.com/biapol/napari-crop
Project-URL: User Support, https://github.com/biapol/napari-crop/issues
Classifier: Development Status :: 3 - Alpha
Classifier: Intended Audience :: Developers
Classifier: Framework :: napari
Classifier: Topic :: Scientific/Engineering :: Image Processing
Classifier: Topic :: Scientific/Engineering :: Information Analysis
Classifier: Programming Language :: Python
Classifier: Programming Language :: Python :: 3
Classifier: Programming Language :: Python :: 3.10
Classifier: Programming Language :: Python :: 3.11
Classifier: Programming Language :: Python :: 3.12
Classifier: Operating System :: OS Independent
Classifier: License :: OSI Approved :: BSD License
Requires-Python: >=3.10
License-File: LICENSE
Requires-Dist: napari-plugin-engine>=0.1.4
Requires-Dist: numpy
Requires-Dist: scikit-image
Requires-Dist: napari-tools-menu>=0.1.17
Requires-Dist: napari-workflows
Provides-Extra: testing
Requires-Dist: tox; extra == "testing"
Requires-Dist: pytest; extra == "testing"
Requires-Dist: pytest-cov; extra == "testing"
Requires-Dist: pytest-qt; extra == "testing"
Requires-Dist: napari; extra == "testing"
Requires-Dist: pyqt5; extra == "testing"
Dynamic: license-file
